README.rst
setup.py
docs/HISTORY.txt
fullmarks/__init__.py
fullmarks.tinymceplugins.asciimath.egg-info/PKG-INFO
fullmarks.tinymceplugins.asciimath.egg-info/SOURCES.txt
fullmarks.tinymceplugins.asciimath.egg-info/dependency_links.txt
fullmarks.tinymceplugins.asciimath.egg-info/entry_points.txt
fullmarks.tinymceplugins.asciimath.egg-info/namespace_packages.txt
fullmarks.tinymceplugins.asciimath.egg-info/not-zip-safe
fullmarks.tinymceplugins.asciimath.egg-info/requires.txt
fullmarks.tinymceplugins.asciimath.egg-info/top_level.txt
fullmarks/tinymceplugins/__init__.py
fullmarks/tinymceplugins/asciimath/__init__.py
fullmarks/tinymceplugins/asciimath/configure.zcml
fullmarks/tinymceplugins/asciimath/profiles.zcml
fullmarks/tinymceplugins/asciimath/skins.zcml
fullmarks/tinymceplugins/asciimath/profiles/default/cssregistry.xml
fullmarks/tinymceplugins/asciimath/profiles/default/fullmarks.tinymceplugins.asciimath_various.txt
fullmarks/tinymceplugins/asciimath/profiles/default/jsregistry.xml
fullmarks/tinymceplugins/asciimath/profiles/default/metadata.xml
fullmarks/tinymceplugins/asciimath/profiles/default/skins.xml
fullmarks/tinymceplugins/asciimath/profiles/default/tinymce.xml
fullmarks/tinymceplugins/asciimath/skins/tinymce_plugin_asciimath/asciimath/amcharmap.htm
fullmarks/tinymceplugins/asciimath/skins/tinymce_plugin_asciimath/asciimath/ampopup.htm.pt
fullmarks/tinymceplugins/asciimath/skins/tinymce_plugin_asciimath/asciimath/editor_plugin.js
fullmarks/tinymceplugins/asciimath/skins/tinymce_plugin_asciimath/asciimath/css/asciimath.css.dtml
fullmarks/tinymceplugins/asciimath/skins/tinymce_plugin_asciimath/asciimath/img/Thumbs.db
fullmarks/tinymceplugins/asciimath/skins/tinymce_plugin_asciimath/asciimath/img/ed_mathformula.gif
fullmarks/tinymceplugins/asciimath/skins/tinymce_plugin_asciimath/asciimath/img/ed_mathformula2.gif
fullmarks/tinymceplugins/asciimath/skins/tinymce_plugin_asciimath/asciimath/js/ASCIIMathML.js
fullmarks/tinymceplugins/asciimath/skins/tinymce_plugin_asciimath/asciimath/js/amcharmap.js
fullmarks/tinymceplugins/asciimath/skins/tinymce_plugin_asciimath/asciimath/js/ampopup.js
fullmarks/tinymceplugins/asciimath/skins/tinymce_plugin_asciimath/asciimath/js/configuremath.js
fullmarks/tinymceplugins/asciimath/skins/tinymce_plugin_asciimath/asciimath/langs/en.js
fullmarks/tinymceplugins/asciimath/skins/tinymce_plugin_asciimath/asciimath/langs/en_dlg.js