Metadata-Version: 1.0
Name: fullmarks.tinymceplugins.asciimath
Version: 1.2
Summary: TinyMCE ASCIIMATH Plugin for Plone
Home-page: http://github.com/fullmarks
Author: Roché Compaan
Author-email: roche@upfrontsystems.co.za
License: GPL
Keywords: plone math asciimath mathml tinymce
Platform: UNKNOWN
Classifier: Framework :: Plone
Classifier: Programming Language :: Python
